eunomia_core/__init__.py
eunomia_core/utils.py
eunomia_core/enums/__init__.py
eunomia_core/enums/entity.py
eunomia_core/enums/policy.py
eunomia_core/schemas/__init__.py
eunomia_core/schemas/check.py
eunomia_core/schemas/entity.py
eunomia_core/schemas/passport.py
eunomia_core/schemas/policy.py
eunomia_core-0.3.10.dist-info/METADATA
eunomia_core-0.3.10.dist-info/WHEEL
eunomia_core-0.3.10.dist-info/RECORD
