Metadata-Version: 2.4
Name: eunomia-core
Version: 0.3.10
Summary: Shared functionalities for Eunomia packages
Author-email: What About You team <info@whataboutyou.ai>
License-Expression: Apache-2.0
Requires-Python: >=3.10
Requires-Dist: pydantic>=2.10.6
